qr_pay/__init__.py
qr_pay/crc.py
qr_pay/fields.py
qr_pay/qr_pay.py
qr_pay/utils.py
napas_qr_python-0.1.2.dist-info/LICENSE
napas_qr_python-0.1.2.dist-info/METADATA
napas_qr_python-0.1.2.dist-info/WHEEL
napas_qr_python-0.1.2.dist-info/entry_points.txt
napas_qr_python-0.1.2.dist-info/RECORD
